fastapi_depends_anywhere/__init__.py
fastapi_depends_anywhere/_internal.py
fastapi_depends_anywhere/config.py
fastapi_depends_anywhere/core.py
fastapi_depends_anywhere/lifecycle.py
fastapi_depends_anywhere/py.typed
fastapi_depends_anywhere/runners.py
fastapi_depends_anywhere-1.1.2.dist-info/METADATA
fastapi_depends_anywhere-1.1.2.dist-info/WHEEL
fastapi_depends_anywhere-1.1.2.dist-info/licenses/LICENSE
fastapi_depends_anywhere-1.1.2.dist-info/RECORD
