Metadata-Version: 2.4
Name: fastapi-depends-anywhere
Version: 1.1.2
Summary: Run FastAPI dependency injection anywhere - in background tasks, scripts, and tests
Project-URL: Homepage, https://github.com/ADR-007/fastapi-depends-anywhere
Project-URL: Repository, https://github.com/ADR-007/fastapi-depends-anywhere
Project-URL: Issues, https://github.com/ADR-007/fastapi-depends-anywhere/issues
Author-email: Adrian Dankiv <adr-007@ukr.net>
License: MIT
License-File: LICENSE
Keywords: background-tasks,dependencies,dependency-injection,fastapi
Classifier: Development Status :: 4 - Beta
Classifier: Framework :: FastAPI
Classifier: Intended Audience :: Developers
Classifier: License :: OSI Approved :: MIT License
Classifier: Programming Language :: Python :: 3
Classifier: Programming Language :: Python :: 3.12
Classifier: Programming Language :: Python :: 3.13
Classifier: Programming Language :: Python :: 3.14
Requires-Python: >=3.12
Requires-Dist: fastapi>=0.115.0
Provides-Extra: all
Requires-Dist: asyncer>=0.0.10; extra == 'all'
Provides-Extra: asyncer
Requires-Dist: asyncer>=0.0.10; extra == 'asyncer'
Provides-Extra: build
Requires-Dist: uv>=0.9.0; extra == 'build'
